napalm_ciena_saos/__init__.py
napalm_ciena_saos/ciena_saos.py
napalm_ciena_saos/utils/__init__.py
napalm_ciena_saos-0.1.0.dist-info/AUTHORS
napalm_ciena_saos-0.1.0.dist-info/LICENSE
napalm_ciena_saos-0.1.0.dist-info/METADATA
napalm_ciena_saos-0.1.0.dist-info/WHEEL
napalm_ciena_saos-0.1.0.dist-info/top_level.txt
napalm_ciena_saos-0.1.0.dist-info/RECORD
