Metadata-Version: 2.1
Name: napalm-ciena-saos
Version: 0.1.0
Summary: Network Automation and Programmability Abstraction Layer with Multivendor support: Ciena SAOS
Home-page: https://github.com/napalm-automation-community/napalm-ciena-saos
Author: Maarten Wallraf
Author-email: maarten@2nms.com
License: UNKNOWN
Platform: UNKNOWN
Classifier: Topic :: Utilities
Classifier: Programming Language :: Python
Classifier: Programming Language :: Python :: 2
Classifier: Programming Language :: Python :: 2.7
Classifier: Programming Language :: Python :: 3.6
Classifier: Programming Language :: Python :: 3.7
Classifier: Programming Language :: Python :: 3.8
Classifier: Operating System :: POSIX :: Linux
Classifier: Operating System :: MacOS
Requires-Dist: napalm (>=2.0.0)
